molli_xt.cpython-311-x86_64-linux-musl.so
molli-1.3.0.dist-info/METADATA
molli-1.3.0.dist-info/top_level.txt
molli-1.3.0.dist-info/entry_points.txt
molli-1.3.0.dist-info/WHEEL
molli-1.3.0.dist-info/RECORD
molli-1.3.0.dist-info/licenses/LICENSE
molli_test/test_external_morfeus.py
molli_test/test_chem_promolecule.py
molli_test/test_external_openbabel.py
molli_test/test_chem_molecule.py
molli_test/test_collections.py
molli_test/test_chem_geometry.py
molli_test/test_descriptor.py
molli_test/test_chem_connectivity.py
molli_test/test_molli_extensions.py
molli_test/test_external_rdkit.py
molli_test/test_conformer_ensemble.py
molli_test/__init__.py
molli_test/test_chem_structure.py
molli_test/test_cdxml_parse.py
molli_test/test_install.py
molli_test/test_read_write.py
molli_test/test_external_xtb.py
molli.libs/libgcc_s-a04fdf82.so.1
molli.libs/libstdc++-a9383cce.so.6.0.28
molli/__main__.py
molli/writer.py
molli/__init__.py
molli/config.py
molli/reader.py
molli/parsing/xyz.py
molli/parsing/mol2.py
molli/parsing/__init__.py
molli/parsing/xtbout.py
molli/parsing/_reader.py
molli/chem/ensemble.py
molli/chem/geometry.py
molli/chem/library.py
molli/chem/__init__.py
molli/chem/atom.py
molli/chem/io.py
molli/chem/molecule.py
molli/chem/legacy.py
molli/chem/structure.py
molli/chem/bond.py
molli/scripts/combine.py
molli/scripts/stats.py
molli/scripts/parse.py
molli/scripts/map.py
molli/scripts/info.py
molli/scripts/__init__.py
molli/scripts/compile.py
molli/scripts/show.py
molli/scripts/pick.py
molli/scripts/grid.py
molli/scripts/run.py
molli/scripts/test.py
molli/scripts/merge.py
molli/scripts/ls.py
molli/scripts/_flask.py
molli/scripts/serve.py
molli/scripts/recollect.py
molli/scripts/gbca.py
molli/scripts/align.py
molli/external/__init__.py
molli/external/rdkit.py
molli/external/openbabel.py
molli/external/morfeus.py
molli/files/fxyl.mol2
molli/files/cinchonidine_mcs.mol2
molli/files/propyne.mol2
molli/files/BOX_bridging_fragments.cdxml
molli/files/cinchonidine.mlib
molli/files/buchwald_cats.cdxml
molli/files/box_alignment_core.mol2
molli/files/charges_mult.cdxml
molli/files/nanotube.mol2
