Metadata-Version: 2.4
Name: molli
Version: 1.3.0
Summary: Molecular toolbox library
Author: Blake E. Ocampo, Elena S. Burlova, Casey L. Olen, N. Ian Rinehart
Author-email: "Alexander S. Shved" <shvedalx@illinois.edu>
License: MIT License
Requires-Python: >=3.10
License-File: LICENSE
Requires-Dist: numpy>=1.24.0
Requires-Dist: scipy>=1.9.1
Requires-Dist: h5py>=3.8
Requires-Dist: msgpack>=1.0.3
Requires-Dist: msgpack-numpy>=0.4.8
Requires-Dist: attrs>=22.1.0
Requires-Dist: bidict>=0.21.2
Requires-Dist: requests>=2.28
Requires-Dist: PyYAML>=5.3
Requires-Dist: colorama>=0.4.4
Requires-Dist: networkx>=3.0
Requires-Dist: tqdm>=4.64.0
Requires-Dist: packaging>=23.1
Requires-Dist: deprecated>=1.2.14
Requires-Dist: fasteners>=0.19
Requires-Dist: joblib>=1.3.2
Dynamic: license-file
